{
  "shape": ".shape {vector-effect: none; stroke-width: 6}",
  "fadedShape": ".fadedShape {vector-effect: none; stroke-width: 6; stroke: #d3d3d3}",
  "grid": ".grid {stroke: #d3d3d3; stroke-width: 0.5; stroke-linecap: butt}",
  "gridCont": ".gridCont {stroke-width: 0}",
  "activeFilled": ".activeFilled {fill: #f00; stroke-width: 1}",
  "text": "text {font-family: Arial, Helvetica Neue, Helvetica, sans-serif; font-size: 16px; stroke-width: 1; fill: #000}",
  "lips": ".lips {fill: none; stroke: #000; stroke-width: 6}",
  "teeth": ".teeth {fill: #000; stroke-width: 0}",
  "fadedTeeth": ".fadedTeeth {fill: #d3d3d3; stroke-width: 0}",
  "copyright": ".copyright {font-size: 25px; stroke-width: 0; fill: #ddd}",
  "bar": ".bar {stroke: #000; stroke-width: 7}",
  "spiral": ".spiral {fill: none; stroke: #000; stroke-width: 5.6; stroke-linecap: round}",
  "diacriticSpiral": ".diacriticSpiral {fill: none; stroke: #000; stroke-width: 4.0; stroke-linecap: round}",
  "spiralBold": ".spiralBold {fill: none; stroke: #000; stroke-width: 7; stroke-linecap: round}",
  "arrow": ".arrow {fill: #000; stroke-width: 0}",
  "arrowTail": ".arrowTail {stroke: #000; stroke-width: 6}",
  "boldLine": ".boldLine {stroke-width: 8}",
  "crossLine": ".crossLine {stroke-width: 5; stroke-linecap: butt}",
  "blackLine": ".blackLine {stroke: #000}",
  "wave": ".wave {stroke-width: 6; stroke: #000; fill: none}",
  "symb": ".symb {stroke-width: 0; fill: #000}",
  "mode": ".mode {fill: #97f765; stroke: #000;}",
  "out": ".out {stroke-width: 1; fill: none;}",
  "supplementaryIndicator": ".supplementaryIndicator {stroke-width: 0; fill: #4682B4}"
}
